{"options":{"check_for_updates":true,"comment":null,"compat_foreach":false,"compat_metadata":false,"compat_powerful_this":null,"compat_wrappedjsobject":false,"compatopts_for_requires":true,"noframes":null,"override":{"merge_connects":true,"merge_excludes":true,"merge_includes":true,"merge_matches":true,"orig_connects":[],"orig_excludes":[],"orig_includes":[],"orig_matches":["https://book.douban.com/*"],"orig_noframes":null,"orig_run_at":"document-idle","use_blockers":[],"use_connects":["qq.com"],"use_excludes":[],"use_includes":[],"use_matches":[]},"run_at":null,"sandbox":null,"tab_types":null,"unwrap":null},"settings":{"enabled":true,"position":50},"meta":{"name":"在豆瓣显示微信读书可读","uuid":"743d90fb-6f08-42f8-b9f4-934eb29fa7cc","modified":1682128921500,"file_url":"https://greasyfork.org/scripts/394514-%E5%9C%A8%E8%B1%86%E7%93%A3%E6%98%BE%E7%A4%BA%E5%BE%AE%E4%BF%A1%E8%AF%BB%E4%B9%A6%E5%8F%AF%E8%AF%BB/code/%E5%9C%A8%E8%B1%86%E7%93%A3%E6%98%BE%E7%A4%BA%E5%BE%AE%E4%BF%A1%E8%AF%BB%E4%B9%A6%E5%8F%AF%E8%AF%BB.user.js"}}